morser/__init__.py
morser/cli.py
morser/dictionary.py
morser-0.1.1.dist-info/entry_points.txt
morser-0.1.1.dist-info/LICENSE
morser-0.1.1.dist-info/METADATA
morser-0.1.1.dist-info/WHEEL
morser-0.1.1.dist-info/RECORD
