Metadata-Version: 2.1
Name: morser
Version: 0.1.1
Summary: Morser is a CLI for encoding and decoding morse code.
License: MIT
Author: Igor Ferreira
Author-email: iferreira.n01@gmail.com
Requires-Python: >=3.11,<4.0
Classifier: Development Status :: 5 - Production/Stable
Classifier: Environment :: Console
Classifier: Intended Audience :: Developers
Classifier: License :: OSI Approved :: MIT License
Classifier: Natural Language :: English
Classifier: Programming Language :: Python :: 3
Classifier: Programming Language :: Python :: 3.11
Requires-Dist: typer[all] (>=0.9.0,<0.10.0)
Project-URL: Bug Tracker, https://github.com/ig0r-ferreira/morser/issues
Project-URL: Source Code, https://github.com/ig0r-ferreira/morser
